autoemxsp/__init__.py
autoemxsp/_custom_plotting.py
autoemxsp/EM_driver/PhenomXL.py
autoemxsp/EM_driver/__init__.py
autoemxsp/Results/K-412_NISTstd_example/Comp_analysis_configs.json
autoemxsp/Results/K-412_NISTstd_example/Data.csv
autoemxsp/Results/K-412_NISTstd_example/NavCam_Ctape.png
autoemxsp/Results/K-412_NISTstd_example/Analysis/Clustering_info.json
autoemxsp/Results/K-412_NISTstd_example/Analysis/Clustering_plot.png
autoemxsp/Results/K-412_NISTstd_example/Analysis/Clusters.csv
autoemxsp/Results/K-412_NISTstd_example/Analysis/Compositions.csv
autoemxsp/Results/K-412_NISTstd_example/Analysis/Silhouette_plot.png
autoemxsp/Results/Wulfenite_example/Comp_analysis_configs.json
autoemxsp/Results/Wulfenite_example/Data.csv
autoemxsp/Results/Wulfenite_example/NavCam_Ctape.png
autoemxsp/Results/Wulfenite_example/Analysis/Clustering_info.json
autoemxsp/Results/Wulfenite_example/Analysis/Clustering_plot.png
autoemxsp/Results/Wulfenite_example/Analysis/Clusters.csv
autoemxsp/Results/Wulfenite_example/Analysis/Compositions.csv
autoemxsp/XSp_calibs/__init__.py
autoemxsp/XSp_calibs/Calibration scripts/Peak_gaussian_sigma_param.py
autoemxsp/XSp_calibs/Microscopes/PhenomXL/EDS_Stds_15keV.json
autoemxsp/XSp_calibs/Microscopes/PhenomXL/XS_calibrations.py
autoemxsp/XSp_calibs/Microscopes/PhenomXL/detector_efficiency.msa
autoemxsp/XSp_calibs/Microscopes/PhenomXL/Detector_channel_params_calibs/20250925_19h08m_detector_channel_params_calibs.json
autoemxsp/XSp_calibs/Microscopes/PhenomXL/Detector_channel_params_calibs/20251218_09h58m_detector_channel_params_calibs.json
autoemxsp/XSp_calibs/Microscopes/PhenomXL/Detector_channel_params_calibs/SDD calibrations/20250923_18h06m/Al/Comp_analysis_configs.json
autoemxsp/XSp_calibs/Microscopes/PhenomXL/Detector_channel_params_calibs/SDD calibrations/20250923_18h06m/Al/Std_measurements.csv
autoemxsp/XSp_calibs/Microscopes/PhenomXL/Detector_channel_params_calibs/SDD calibrations/20250923_18h06m/Al/Std_measurements_20250923_18h06m_50kcnts.csv
autoemxsp-0.1.7.dist-info/licenses/LICENSE.txt
autoemxsp-0.1.7.dist-info/METADATA
autoemxsp-0.1.7.dist-info/WHEEL
autoemxsp-0.1.7.dist-info/top_level.txt
autoemxsp-0.1.7.dist-info/RECORD
