Metadata-Version: 2.4
Name: autoemxsp
Version: 0.1.7
Summary: AutoEMXSp - Automated Electron Microscopy X-Ray Spectroscopy for Compositional Characterization of Materials
Author-email: Andrea Giunto <agiunto@lbl.gov>
License-Expression: LicenseRef-AcademicNonCommercial
Classifier: Programming Language :: Python :: 3
Classifier: Programming Language :: Python :: 3.11
Classifier: Operating System :: OS Independent
Requires-Python: <=3.13,>=3.11
License-File: LICENSE.txt
Requires-Dist: cvxpy<=1.7.3,>=1.5.3
Requires-Dist: ecos>=2.0.14
Requires-Dist: lmfit<=1.3.4,>=1.3.2
Requires-Dist: matplotlib<=3.10.6,>=3.5.2
Requires-Dist: numpy<=2.2.6,>=1.26.4
Requires-Dist: pandas<=2.3.3,>=2.2.2
Requires-Dist: pymatgen<=2025.10.7,>=2024.11.13
Requires-Dist: scikit-learn<=1.7.2,>=1.5.1
Requires-Dist: scipy<=1.16.2,>=1.14.1
Requires-Dist: seaborn<=0.13.2,>=0.13.2
Requires-Dist: sympy<=1.14.0,>=1.13.2
Requires-Dist: yellowbrick==1.5
Requires-Dist: opencv-python<=4.12.0.88,>=4.10.0
Requires-Dist: pillow>=10.0.1
Dynamic: license-file
